pyohio2015/cli.py
pyohio2015/__init__.py
pyohio2015-0.1.0.dist-info/metadata.json
pyohio2015-0.1.0.dist-info/RECORD
pyohio2015-0.1.0.dist-info/DESCRIPTION.rst
pyohio2015-0.1.0.dist-info/top_level.txt
pyohio2015-0.1.0.dist-info/METADATA
pyohio2015-0.1.0.dist-info/WHEEL
