Metadata-Version: 2.0
Name: pyohio2015
Version: 0.1.0
Summary: Example package for PyOhio talk
Home-page: https://github.com/tylerdave/pyohio2015
Author: Dave Forgac
Author-email: tylerdave@tylerdave.com
License: MIT
Keywords: pyohio2015
Platform: UNKNOWN
Classifier: Development Status :: 2 - Pre-Alpha
Classifier: Intended Audience :: Developers
Classifier: License :: OSI Approved :: MIT License
Classifier: Natural Language :: English
Classifier: Programming Language :: Python :: 2
Classifier: Programming Language :: Python :: 2.6
Classifier: Programming Language :: Python :: 2.7
Classifier: Programming Language :: Python :: 3
Classifier: Programming Language :: Python :: 3.3
Classifier: Programming Language :: Python :: 3.4
